unzone.py
unzone-0.1.0.dist-info/licenses/LICENSE
unzone-0.1.0.dist-info/METADATA
unzone-0.1.0.dist-info/WHEEL
unzone-0.1.0.dist-info/entry_points.txt
unzone-0.1.0.dist-info/top_level.txt
unzone-0.1.0.dist-info/RECORD
