Metadata-Version: 2.4
Name: unzone
Version: 0.1.0
Summary: Recursively find and delete Zone.Identifier files created by Windows
Author: Spenser Mcconnell
License-Expression: MIT
Project-URL: Homepage, https://github.com/spenquatch/unzone
Project-URL: Issues, https://github.com/spenquatch/unzone/issues
Keywords: zone-identifier,windows,cleanup,utility,unzone
Classifier: Development Status :: 4 - Beta
Classifier: Intended Audience :: Developers
Classifier: Intended Audience :: System Administrators
Classifier: Operating System :: OS Independent
Classifier: Programming Language :: Python :: 3
Classifier: Programming Language :: Python :: 3.7
Classifier: Programming Language :: Python :: 3.8
Classifier: Programming Language :: Python :: 3.9
Classifier: Programming Language :: Python :: 3.10
Classifier: Programming Language :: Python :: 3.11
Classifier: Programming Language :: Python :: 3.12
Classifier: Topic :: System :: Filesystems
Classifier: Topic :: Utilities
Requires-Python: >=3.7
License-File: LICENSE
Dynamic: license-file
